{"cameraMode":{"drawMode":0,"name":"Shaded","section":"Shading Mode"},"sceneLighting":true,"audioPlay":false,"sceneViewState":{"showFog":true,"showMaterialUpdate":false,"showSkybox":true,"showFlares":true,"showImageEffects":true,"showParticleSystems":true},"in2DMode":false,"pivot":{"x":-1.2217686176300049,"y":-0.9264836311340332,"z":4.253242015838623},"rotation":{"x":0.18346022069454194,"y":-0.05717941373586655,"z":0.010639526881277562,"w":0.9813540577888489},"size":3.101637601852417,"orthographic":false}