{"cameraMode":{"drawMode":0,"name":"Shaded","section":"Shading Mode"},"sceneLighting":true,"audioPlay":false,"sceneViewState":{"showFog":true,"showMaterialUpdate":false,"showSkybox":true,"showFlares":true,"showImageEffects":true,"showParticleSystems":true},"in2DMode":false,"pivot":{"x":-4.1573896408081059,"y":-4.929325103759766,"z":8.470170974731446},"rotation":{"x":-0.18596184253692628,"y":0.28060925006866457,"z":-0.05551522597670555,"w":-0.940005362033844},"size":9.431066513061524,"orthographic":false}